odoo8_addon_sale_payment_method_transaction_id-8.0.1.0.0.99.dev12-py3.8-nspkg.pth
odoo_addons/sale_payment_method_transaction_id/README.rst
odoo_addons/sale_payment_method_transaction_id/__init__.py
odoo_addons/sale_payment_method_transaction_id/__openerp__.py
odoo_addons/sale_payment_method_transaction_id/i18n/ca.po
odoo_addons/sale_payment_method_transaction_id/i18n/de.po
odoo_addons/sale_payment_method_transaction_id/i18n/es.po
odoo_addons/sale_payment_method_transaction_id/i18n/es_ES.po
odoo_addons/sale_payment_method_transaction_id/i18n/fi.po
odoo_addons/sale_payment_method_transaction_id/i18n/fr.po
odoo_addons/sale_payment_method_transaction_id/i18n/hr.po
odoo_addons/sale_payment_method_transaction_id/i18n/hu.po
odoo_addons/sale_payment_method_transaction_id/i18n/it.po
odoo_addons/sale_payment_method_transaction_id/i18n/nl.po
odoo_addons/sale_payment_method_transaction_id/i18n/nl_NL.po
odoo_addons/sale_payment_method_transaction_id/i18n/pt_BR.po
odoo_addons/sale_payment_method_transaction_id/i18n/ro.po
odoo_addons/sale_payment_method_transaction_id/i18n/sale_payment_method_transaction_id.pot
odoo_addons/sale_payment_method_transaction_id/i18n/sk.po
odoo_addons/sale_payment_method_transaction_id/i18n/sl.po
odoo_addons/sale_payment_method_transaction_id/i18n/tr.po
odoo_addons/sale_payment_method_transaction_id/i18n/tr_TR.po
odoo_addons/sale_payment_method_transaction_id/i18n/zh_CN.po
odoo_addons/sale_payment_method_transaction_id/models/__init__.py
odoo_addons/sale_payment_method_transaction_id/models/sale.py
odoo_addons/sale_payment_method_transaction_id/static/description/icon.png
odoo8_addon_sale_payment_method_transaction_id-8.0.1.0.0.99.dev12.dist-info/METADATA
odoo8_addon_sale_payment_method_transaction_id-8.0.1.0.0.99.dev12.dist-info/WHEEL
odoo8_addon_sale_payment_method_transaction_id-8.0.1.0.0.99.dev12.dist-info/namespace_packages.txt
odoo8_addon_sale_payment_method_transaction_id-8.0.1.0.0.99.dev12.dist-info/top_level.txt
odoo8_addon_sale_payment_method_transaction_id-8.0.1.0.0.99.dev12.dist-info/RECORD
